tonic_ragas_logger/__init__.py
tonic_ragas_logger/config.py
tonic_ragas_logger/ragas_validate_api.py
tonic_ragas_logger/utils/__init__.py
tonic_ragas_logger/utils/http_client.py
tonic_ragas_logger/utils/telemetry.py
tonic_ragas_logger-1.2.3.dist-info/LICENSE
tonic_ragas_logger-1.2.3.dist-info/METADATA
tonic_ragas_logger-1.2.3.dist-info/WHEEL
tonic_ragas_logger-1.2.3.dist-info/RECORD
