Metadata-Version: 2.1
Name: tonic-ragas-logger
Version: 1.2.3
Summary: Uploads results from ragas to Tonic Validate.
Requires-Python: >=3.8.1,<4.0.0
Classifier: Programming Language :: Python :: 3
Classifier: Programming Language :: Python :: 3.9
Classifier: Programming Language :: Python :: 3.10
Classifier: Programming Language :: Python :: 3.11
Classifier: Programming Language :: Python :: 3.12
Classifier: Programming Language :: Python :: 3.13
Requires-Dist: python-dotenv (>=1.0.1,<2.0.0)
Requires-Dist: ragas (>=0.1.2,<0.2.0)
Requires-Dist: tonic-validate (>=6.1.1)
